LICENSE.txt
Makefile
README.rst
pyproject.toml
tox.ini
mlmorph/__init__.py
mlmorph/__main__.py
mlmorph/analyser.py
mlmorph/foreign_word_detector.py
mlmorph/generator.py
mlmorph/normalizer.py
mlmorph/utils.py
mlmorph.egg-info/PKG-INFO
mlmorph.egg-info/SOURCES.txt
mlmorph.egg-info/dependency_links.txt
mlmorph.egg-info/entry_points.txt
mlmorph.egg-info/requires.txt
mlmorph.egg-info/top_level.txt
mlmorph/data/malayalam.a
mlmorph/spellchecker/__init__.py
mlmorph/spellchecker/__main__.py
mlmorph/spellchecker/spellchecker.py
mlmorph/spellchecker/suggestion.py
mlmorph/spellchecker/utils.py
mlmorph/spellchecker/resources/README.md
mlmorph/spellchecker/resources/common_mistakes.csv
mlmorph/spellchecker/strategies/__init__.py
mlmorph/spellchecker/strategies/chillu_normalization.py
mlmorph/spellchecker/strategies/chillu_to_virama_form.py
mlmorph/spellchecker/strategies/consonant_virama_to_chillu.py
mlmorph/spellchecker/strategies/geminate_consonants.py
mlmorph/spellchecker/strategies/insert_y_before_kkuka.py
mlmorph/spellchecker/strategies/mpa_correction.py
mlmorph/spellchecker/strategies/nta_correction.py
mlmorph/spellchecker/strategies/phonetic_similarity.py
mlmorph/spellchecker/strategies/suggestion_strategy.py
mlmorph/spellchecker/strategies/virama_insertion.py
mlmorph/spellchecker/strategies/visual_similarity.py
mlmorph/spellchecker/strategies/vowel_elongation.py
mlmorph/spellchecker/strategies/vowel_shortening.py
test/unit/test_mlmorph.py
test/unit/spellchecker/__init__.py
test/unit/spellchecker/test_spellchecker.py