Metadata-Version: 2.1
Name: mlmorph
Version: 1.4.0
Summary: Malayalam morphology analyser
Author-email: Santhosh Thottingal <santhosh.thottingal@gmail.com>
Keywords: Malayalam,morphology,FST,analyser,generator,spellchecker
Classifier: Programming Language :: Python :: 3
Classifier: Programming Language :: Python :: 3.8
Classifier: Programming Language :: Python :: 3.9
Classifier: Programming Language :: Python :: 3.10
Classifier: Programming Language :: Python :: 3.11
Classifier: Programming Language :: Python :: 3.12
Classifier: License :: OSI Approved :: MIT License
Classifier: Intended Audience :: Developers
Requires-Python: >=3.8
License-File: LICENSE.txt
Requires-Dist: regex
Requires-Dist: sfst>=1.6.0
Provides-Extra: tests
Requires-Dist: pytest; extra == "tests"
Provides-Extra: dev
Requires-Dist: ruff>=0.6.4; extra == "dev"
Requires-Dist: tox; extra == "dev"
Requires-Dist: build; extra == "dev"
Requires-Dist: twine; extra == "dev"
